{"JetStream2.0":{"metrics":{"Score":["Geometric"]},"tests":{"WSL":{"metrics":{"Score":{"current":[0.9121900813362481]},"Time":["Geometric"]},"tests":{"Stdlib":{"metrics":{"Time":{"current":[3664]}}},"MainRun":{"metrics":{"Time":{"current":[8200]}}}}},"UniPoker":{"metrics":{"Score":{"current":[359.0724483386472]},"Time":["Geometric"]},"tests":{"First":{"metrics":{"Time":{"current":[24]}}},"Worst":{"metrics":{"Time":{"current":[11.25]}}},"Average":{"metrics":{"Time":{"current":[10]}}}}},"uglify-js-wtb":{"metrics":{"Score":{"current":[27.767839762723025]},"Time":["Geometric"]},"tests":{"First":{"metrics":{"Time":{"current":[216]}}},"Worst":{"metrics":{"Time":{"current":[179]}}},"Average":{"metrics":{"Time":{"current":[151.00000000000003]}}}}},"typescript":{"metrics":{"Score":{"current":[13.552167452804744]},"Time":["Geometric"]},"tests":{"First":{"metrics":{"Time":{"current":[506.99999999999994]}}},"Worst":{"metrics":{"Time":{"current":[334]}}},"Average":{"metrics":{"Time":{"current":[296.57142857142856]}}}}},"tsf-wasm":{"metrics":{"Score":{"current":[85.85035246793063]},"Time":["Geometric"]},"tests":{"Startup":{"metrics":{"Time":{"current":[16]}}},"Runtime":{"metrics":{"Time":{"current":[212]}}}}},"tagcloud-SP":{"metrics":{"Score":{"current":[202.70867141110543]},"Time":["Geometric"]},"tests":{"First":{"metrics":{"Time":{"current":[42]}}},"Worst":{"metrics":{"Time":{"current":[22.75]}}},"Average":{"metrics":{"Time":{"current":[15.705882352941174]}}}}},"string-unpack-code-SP":{"metrics":{"Score":{"current":[232.95002216664216]},"Time":["Geometric"]},"tests":{"First":{"metrics":{"Time":{"current":[26]}}},"Worst":{"metrics":{"Time":{"current":[28.499999999999996]}}},"Average":{"metrics":{"Time":{"current":[13.344537815126051]}}}}},"stanford-crypto-sha256":{"metrics":{"Score":{"current":[484.60911710768556]},"Time":["Geometric"]},"tests":{"First":{"metrics":{"Time":{"current":[13]}}},"Worst":{"metrics":{"Time":{"current":[11]}}},"Average":{"metrics":{"Time":{"current":[7.680672268907563]}}}}},"stanford-crypto-pbkdf2":{"metrics":{"Score":{"current":[427.02445476435537]},"Time":["Geometric"]},"tests":{"First":{"metrics":{"Time":{"current":[11]}}},"Worst":{"metrics":{"Time":{"current":[13.75]}}},"Average":{"metrics":{"Time":{"current":[10.61344537815126]}}}}},"stanford-crypto-aes":{"metrics":{"Score":{"current":[354.919918699131]},"Time":["Geometric"]},"tests":{"First":{"metrics":{"Time":{"current":[20]}}},"Worst":{"metrics":{"Time":{"current":[12.25]}}},"Average":{"metrics":{"Time":{"current":[11.411764705882353]}}}}},"splay":{"metrics":{"Score":{"current":[191.2646803226605]},"Time":["Geometric"]},"tests":{"First":{"metrics":{"Time":{"current":[19]}}},"Worst":{"metrics":{"Time":{"current":[44]}}},"Average":{"metrics":{"Time":{"current":[21.369747899159663]}}}}},"segmentation":{"metrics":{"Score":{"current":[35.27490693183812]},"Time":["Geometric"]},"tests":{"First":{"metrics":{"Time":{"current":[195]}}},"Worst":{"metrics":{"Time":{"current":[137]}}},"Average":{"metrics":{"Time":{"current":[106.6]}}}}},"richards-wasm":{"metrics":{"Score":{"current":[50.46644692950626]},"Time":["Geometric"]},"tests":{"Startup":{"metrics":{"Time":{"current":[12]}}},"Runtime":{"metrics":{"Time":{"current":[818]}}}}},"richards":{"metrics":{"Score":{"current":[331.0857427819107]},"Time":["Geometric"]},"tests":{"First":{"metrics":{"Time":{"current":[18]}}},"Worst":{"metrics":{"Time":{"current":[15]}}},"Average":{"metrics":{"Time":{"current":[12.756302521008404]}}}}},"regexp":{"metrics":{"Score":{"current":[335.0042675341417]},"Time":["Geometric"]},"tests":{"First":{"metrics":{"Time":{"current":[13]}}},"Worst":{"metrics":{"Time":{"current":[23.25]}}},"Average":{"metrics":{"Time":{"current":[11]}}}}},"regex-dna-SP":{"metrics":{"Score":{"current":[518.790026708125]},"Time":["Geometric"]},"tests":{"First":{"metrics":{"Time":{"current":[10]}}},"Worst":{"metrics":{"Time":{"current":[10.75]}}},"Average":{"metrics":{"Time":{"current":[8.327731092436975]}}}}},"raytrace":{"metrics":{"Score":{"current":[328.2646582379605]},"Time":["Geometric"]},"tests":{"First":{"metrics":{"Time":{"current":[27.999999999999996]}}},"Worst":{"metrics":{"Time":{"current":[12.25]}}},"Average":{"metrics":{"Time":{"current":[10.302521008403362]}}}}},"quicksort-wasm":{"metrics":{"Score":{"current":[322.74861218395137]},"Time":["Geometric"]},"tests":{"Startup":{"metrics":{"Time":{"current":[8]}}},"Runtime":{"metrics":{"Time":{"current":[30]}}}}},"prepack-wtb":{"metrics":{"Score":{"current":[46.65334747153694]},"Time":["Geometric"]},"tests":{"First":{"metrics":{"Time":{"current":[152]}}},"Worst":{"metrics":{"Time":{"current":[95]}}},"Average":{"metrics":{"Time":{"current":[85.25]}}}}},"pdfjs":{"metrics":{"Score":{"current":[159.83830909537707]},"Time":["Geometric"]},"tests":{"First":{"metrics":{"Time":{"current":[50.99999999999999]}}},"Worst":{"metrics":{"Time":{"current":[31]}}},"Average":{"metrics":{"Time":{"current":[19.361344537815125]}}}}},"OfflineAssembler":{"metrics":{"Score":{"current":[54.2070240446675]},"Time":["Geometric"]},"tests":{"First":{"metrics":{"Time":{"current":[93]}}},"Worst":{"metrics":{"Time":{"current":[106]}}},"Average":{"metrics":{"Time":{"current":[79.60759493670886]}}}}},"octane-zlib":{"metrics":{"Score":{"current":[23.62031955702101]},"Time":["Geometric"]},"tests":{"First":{"metrics":{"Time":{"current":[248]}}},"Worst":{"metrics":{"Time":{"current":[196.5]}}},"Average":{"metrics":{"Time":{"current":[194.64285714285714]}}}}},"octane-code-load":{"metrics":{"Score":{"current":[824.6971332220195]},"Time":["Geometric"]},"tests":{"First":{"metrics":{"Time":{"current":[6]}}},"Worst":{"metrics":{"Time":{"current":[8.5]}}},"Average":{"metrics":{"Time":{"current":[4.369747899159663]}}}}},"navier-stokes":{"metrics":{"Score":{"current":[595.1840260936415]},"Time":["Geometric"]},"tests":{"First":{"metrics":{"Time":{"current":[18]}}},"Worst":{"metrics":{"Time":{"current":[6.5]}}},"Average":{"metrics":{"Time":{"current":[5.067226890756302]}}}}},"n-body-SP":{"metrics":{"Score":{"current":[854.3900794557087]},"Time":["Geometric"]},"tests":{"First":{"metrics":{"Time":{"current":[6]}}},"Worst":{"metrics":{"Time":{"current":[7.5]}}},"Average":{"metrics":{"Time":{"current":[4.453781512605042]}}}}},"multi-inspector-code-load":{"metrics":{"Score":{"current":[159.6338842969959]},"Time":["Geometric"]},"tests":{"First":{"metrics":{"Time":{"current":[31]}}},"Worst":{"metrics":{"Time":{"current":[37]}}},"Average":{"metrics":{"Time":{"current":[26.789915966386555]}}}}},"ML":{"metrics":{"Score":{"current":[38.4260842524281]},"Time":["Geometric"]},"tests":{"First":{"metrics":{"Time":{"current":[140]}}},"Worst":{"metrics":{"Time":{"current":[126.74999999999999]}}},"Average":{"metrics":{"Time":{"current":[124.15254237288136]}}}}},"mandreel":{"metrics":{"Score":{"current":[55.48122358725517]},"Time":["Geometric"]},"tests":{"First":{"metrics":{"Time":{"current":[126]}}},"Worst":{"metrics":{"Time":{"current":[78.5]}}},"Average":{"metrics":{"Time":{"current":[74]}}}}},"lebab-wtb":{"metrics":{"Score":{"current":[54.866340639133945]},"Time":["Geometric"]},"tests":{"First":{"metrics":{"Time":{"current":[126]}}},"Worst":{"metrics":{"Time":{"current":[82]}}},"Average":{"metrics":{"Time":{"current":[73.25]}}}}},"json-stringify-inspector":{"metrics":{"Score":{"current":[282.2524885345114]},"Time":["Geometric"]},"tests":{"First":{"metrics":{"Time":{"current":[17]}}},"Worst":{"metrics":{"Time":{"current":[19]}}},"Average":{"metrics":{"Time":{"current":[17.210526315789473]}}}}},"json-parse-inspector":{"metrics":{"Score":{"current":[170.33201916362154]},"Time":["Geometric"]},"tests":{"First":{"metrics":{"Time":{"current":[22]}}},"Worst":{"metrics":{"Time":{"current":[42.5]}}},"Average":{"metrics":{"Time":{"current":[27.05263157894737]}}}}},"jshint-wtb":{"metrics":{"Score":{"current":[64.44828290937365]},"Time":["Geometric"]},"tests":{"First":{"metrics":{"Time":{"current":[109]}}},"Worst":{"metrics":{"Time":{"current":[68]}}},"Average":{"metrics":{"Time":{"current":[63]}}}}},"HashSet-wasm":{"metrics":{"Score":{"current":[30.98485830098972]},"Time":["Geometric"]},"tests":{"Startup":{"metrics":{"Time":{"current":[13.999999999999998]}}},"Runtime":{"metrics":{"Time":{"current":[1860.0000000000002]}}}}},"hash-map":{"metrics":{"Score":{"current":[195.31054197919912]},"Time":["Geometric"]},"tests":{"First":{"metrics":{"Time":{"current":[27]}}},"Worst":{"metrics":{"Time":{"current":[33.75]}}},"Average":{"metrics":{"Time":{"current":[18.41176470588235]}}}}},"gcc-loops-wasm":{"metrics":{"Score":{"current":[27.350595182777727]},"Time":["Geometric"]},"tests":{"Startup":{"metrics":{"Time":{"current":[10]}}},"Runtime":{"metrics":{"Time":{"current":[3342]}}}}},"gbemu":{"metrics":{"Score":{"current":[116.36100733046432]},"Time":["Geometric"]},"tests":{"First":{"metrics":{"Time":{"current":[90]}}},"Worst":{"metrics":{"Time":{"current":[36]}}},"Average":{"metrics":{"Time":{"current":[24.48739495798319]}}}}},"gaussian-blur":{"metrics":{"Score":{"current":[389.2642075951355]},"Time":["Geometric"]},"tests":{"First":{"metrics":{"Time":{"current":[15]}}},"Worst":{"metrics":{"Time":{"current":[12.5]}}},"Average":{"metrics":{"Time":{"current":[11.302521008403362]}}}}},"float-mm.c":{"metrics":{"Score":{"current":[9.941823411766267]},"Time":["Geometric"]},"tests":{"First":{"metrics":{"Time":{"current":[499]}}},"Worst":{"metrics":{"Time":{"current":[513]}}},"Average":{"metrics":{"Time":{"current":[496.9285714285715]}}}}},"FlightPlanner":{"metrics":{"Score":{"current":[592.0288830087252]},"Time":["Geometric"]},"tests":{"First":{"metrics":{"Time":{"current":[18]}}},"Worst":{"metrics":{"Time":{"current":[6.75]}}},"Average":{"metrics":{"Time":{"current":[4.957983193277311]}}}}},"first-inspector-code-load":{"metrics":{"Score":{"current":[165.31328609224474]},"Time":["Geometric"]},"tests":{"First":{"metrics":{"Time":{"current":[30]}}},"Worst":{"metrics":{"Time":{"current":[34]}}},"Average":{"metrics":{"Time":{"current":[27.126050420168067]}}}}},"espree-wtb":{"metrics":{"Score":{"current":[27.258265470299634]},"Time":["Geometric"]},"tests":{"First":{"metrics":{"Time":{"current":[265]}}},"Worst":{"metrics":{"Time":{"current":[170]}}},"Average":{"metrics":{"Time":{"current":[137]}}}}},"earley-boyer":{"metrics":{"Score":{"current":[223.3597506188717]},"Time":["Geometric"]},"tests":{"First":{"metrics":{"Time":{"current":[18]}}},"Worst":{"metrics":{"Time":{"current":[48]}}},"Average":{"metrics":{"Time":{"current":[12.983193277310924]}}}}},"delta-blue":{"metrics":{"Score":{"current":[370.7900850863315]},"Time":["Geometric"]},"tests":{"First":{"metrics":{"Time":{"current":[22]}}},"Worst":{"metrics":{"Time":{"current":[13.25]}}},"Average":{"metrics":{"Time":{"current":[8.411764705882353]}}}}},"date-format-xparb-SP":{"metrics":{"Score":{"current":[187.72175285497607]},"Time":["Geometric"]},"tests":{"First":{"metrics":{"Time":{"current":[30]}}},"Worst":{"metrics":{"Time":{"current":[26.75]}}},"Average":{"metrics":{"Time":{"current":[23.54621848739496]}}}}},"date-format-tofte-SP":{"metrics":{"Score":{"current":[132.81129834527397]},"Time":["Geometric"]},"tests":{"First":{"metrics":{"Time":{"current":[43]}}},"Worst":{"metrics":{"Time":{"current":[37]}}},"Average":{"metrics":{"Time":{"current":[33.53781512605042]}}}}},"crypto-sha1-SP":{"metrics":{"Score":{"current":[282.5148097594985]},"Time":["Geometric"]},"tests":{"First":{"metrics":{"Time":{"current":[20]}}},"Worst":{"metrics":{"Time":{"current":[19]}}},"Average":{"metrics":{"Time":{"current":[14.588235294117647]}}}}},"crypto-md5-SP":{"metrics":{"Score":{"current":[223.03541364187777]},"Time":["Geometric"]},"tests":{"First":{"metrics":{"Time":{"current":[27]}}},"Worst":{"metrics":{"Time":{"current":[24]}}},"Average":{"metrics":{"Time":{"current":[17.386554621848738]}}}}},"crypto-aes-SP":{"metrics":{"Score":{"current":[335.6034187484027]},"Time":["Geometric"]},"tests":{"First":{"metrics":{"Time":{"current":[23]}}},"Worst":{"metrics":{"Time":{"current":[14.750000000000002]}}},"Average":{"metrics":{"Time":{"current":[9.747899159663863]}}}}},"crypto":{"metrics":{"Score":{"current":[605.5711924474908]},"Time":["Geometric"]},"tests":{"First":{"metrics":{"Time":{"current":[13]}}},"Worst":{"metrics":{"Time":{"current":[7.5]}}},"Average":{"metrics":{"Time":{"current":[5.773109243697479]}}}}},"coffeescript-wtb":{"metrics":{"Score":{"current":[47.597933187480294]},"Time":["Geometric"]},"tests":{"First":{"metrics":{"Time":{"current":[145]}}},"Worst":{"metrics":{"Time":{"current":[99]}}},"Average":{"metrics":{"Time":{"current":[80.75]}}}}},"chai-wtb":{"metrics":{"Score":{"current":[91.43642595234624]},"Time":["Geometric"]},"tests":{"First":{"metrics":{"Time":{"current":[71]}}},"Worst":{"metrics":{"Time":{"current":[49]}}},"Average":{"metrics":{"Time":{"current":[47]}}}}},"cdjs":{"metrics":{"Score":{"current":[53.96078969528103]},"Time":["Geometric"]},"tests":{"First":{"metrics":{"Time":{"current":[99]}}},"Worst":{"metrics":{"Time":{"current":[98]}}},"Average":{"metrics":{"Time":{"current":[82]}}}}},"Box2D":{"metrics":{"Score":{"current":[277.68937847900264]},"Time":["Geometric"]},"tests":{"First":{"metrics":{"Time":{"current":[53]}}},"Worst":{"metrics":{"Time":{"current":[12.749999999999998]}}},"Average":{"metrics":{"Time":{"current":[8.638655462184873]}}}}},"bomb-workers":{"metrics":{"Score":{"current":[35.946791032877556]},"Time":["Geometric"]},"tests":{"First":{"metrics":{"Time":{"current":[130]}}},"Worst":{"metrics":{"Time":{"current":[160]}}},"Average":{"metrics":{"Time":{"current":[129.37974683544303]}}}}},"Basic":{"metrics":{"Score":{"current":[423.6932835433227]},"Time":["Geometric"]},"tests":{"First":{"metrics":{"Time":{"current":[20]}}},"Worst":{"metrics":{"Time":{"current":[10.25]}}},"Average":{"metrics":{"Time":{"current":[8.016806722689076]}}}}},"base64-SP":{"metrics":{"Score":{"current":[582.9802979367715]},"Time":["Geometric"]},"tests":{"First":{"metrics":{"Time":{"current":[11]}}},"Worst":{"metrics":{"Time":{"current":[8.75]}}},"Average":{"metrics":{"Time":{"current":[6.554621848739496]}}}}},"babylon-wtb":{"metrics":{"Score":{"current":[36.32142690528211]},"Time":["Geometric"]},"tests":{"First":{"metrics":{"Time":{"current":[161]}}},"Worst":{"metrics":{"Time":{"current":[132]}}},"Average":{"metrics":{"Time":{"current":[122.75000000000001]}}}}},"Babylon":{"metrics":{"Score":{"current":[310.7615564611586]},"Time":["Geometric"]},"tests":{"First":{"metrics":{"Time":{"current":[50]}}},"Worst":{"metrics":{"Time":{"current":[11.5]}}},"Average":{"metrics":{"Time":{"current":[7.243697478991597]}}}}},"async-fs":{"metrics":{"Score":{"current":[113.14804059586591]},"Time":["Geometric"]},"tests":{"First":{"metrics":{"Time":{"current":[46]}}},"Worst":{"metrics":{"Time":{"current":[46.333333333333336]}}},"Average":{"metrics":{"Time":{"current":[40.48717948717949]}}}}},"Air":{"metrics":{"Score":{"current":[322.7832366631664]},"Time":["Geometric"]},"tests":{"First":{"metrics":{"Time":{"current":[33]}}},"Worst":{"metrics":{"Time":{"current":[15.75]}}},"Average":{"metrics":{"Time":{"current":[7.15126050420168]}}}}},"ai-astar":{"metrics":{"Score":{"current":[486.9425680860843]},"Time":["Geometric"]},"tests":{"First":{"metrics":{"Time":{"current":[11]}}},"Worst":{"metrics":{"Time":{"current":[12]}}},"Average":{"metrics":{"Time":{"current":[8.201680672268907]}}}}},"acorn-wtb":{"metrics":{"Score":{"current":[32.22655712993761]},"Time":["Geometric"]},"tests":{"First":{"metrics":{"Time":{"current":[172]}}},"Worst":{"metrics":{"Time":{"current":[154]}}},"Average":{"metrics":{"Time":{"current":[141]}}}}},"3d-raytrace-SP":{"metrics":{"Score":{"current":[261.8585952861118]},"Time":["Geometric"]},"tests":{"First":{"metrics":{"Time":{"current":[25]}}},"Worst":{"metrics":{"Time":{"current":[17.25]}}},"Average":{"metrics":{"Time":{"current":[16.142857142857142]}}}}},"3d-cube-SP":{"metrics":{"Score":{"current":[245.36370338238947]},"Time":["Geometric"]},"tests":{"First":{"metrics":{"Time":{"current":[24]}}},"Worst":{"metrics":{"Time":{"current":[20.25]}}},"Average":{"metrics":{"Time":{"current":[17.41176470588235]}}}}}}}}