{"JetStream2.0":{"metrics":{"Score":["Geometric"]},"tests":{"WSL":{"metrics":{"Score":{"current":[0.7721231045352354]},"Time":["Geometric"]},"tests":{"Stdlib":{"metrics":{"Time":{"current":[4341]}}},"MainRun":{"metrics":{"Time":{"current":[9660]}}}}},"UniPoker":{"metrics":{"Score":{"current":[310.3654822722559]},"Time":["Geometric"]},"tests":{"First":{"metrics":{"Time":{"current":[25]}}},"Worst":{"metrics":{"Time":{"current":[15.5]}}},"Average":{"metrics":{"Time":{"current":[10.789915966386555]}}}}},"uglify-js-wtb":{"metrics":{"Score":{"current":[24.981267690383493]},"Time":["Geometric"]},"tests":{"First":{"metrics":{"Time":{"current":[260]}}},"Worst":{"metrics":{"Time":{"current":[178]}}},"Average":{"metrics":{"Time":{"current":[173.25]}}}}},"typescript":{"metrics":{"Score":{"current":[12.402335992147908]},"Time":["Geometric"]},"tests":{"First":{"metrics":{"Time":{"current":[510.99999999999994]}}},"Worst":{"metrics":{"Time":{"current":[395.5]}}},"Average":{"metrics":{"Time":{"current":[324.2142857142857]}}}}},"tsf-wasm":{"metrics":{"Score":{"current":[98.7633246886238]},"Time":["Geometric"]},"tests":{"Startup":{"metrics":{"Time":{"current":[11]}}},"Runtime":{"metrics":{"Time":{"current":[233.00000000000003]}}}}},"tagcloud-SP":{"metrics":{"Score":{"current":[187.19781197866826]},"Time":["Geometric"]},"tests":{"First":{"metrics":{"Time":{"current":[47]}}},"Worst":{"metrics":{"Time":{"current":[23.5]}}},"Average":{"metrics":{"Time":{"current":[17.252100840336134]}}}}},"string-unpack-code-SP":{"metrics":{"Score":{"current":[249.66041344060795]},"Time":["Geometric"]},"tests":{"First":{"metrics":{"Time":{"current":[26]}}},"Worst":{"metrics":{"Time":{"current":[21.5]}}},"Average":{"metrics":{"Time":{"current":[14.369747899159664]}}}}},"stanford-crypto-sha256":{"metrics":{"Score":{"current":[523.3828262862397]},"Time":["Geometric"]},"tests":{"First":{"metrics":{"Time":{"current":[10]}}},"Worst":{"metrics":{"Time":{"current":[11.75]}}},"Average":{"metrics":{"Time":{"current":[7.420168067226891]}}}}},"stanford-crypto-pbkdf2":{"metrics":{"Score":{"current":[361.2258578265814]},"Time":["Geometric"]},"tests":{"First":{"metrics":{"Time":{"current":[13.999999999999998]}}},"Worst":{"metrics":{"Time":{"current":[17]}}},"Average":{"metrics":{"Time":{"current":[11.142857142857142]}}}}},"stanford-crypto-aes":{"metrics":{"Score":{"current":[297.7416427295051]},"Time":["Geometric"]},"tests":{"First":{"metrics":{"Time":{"current":[22]}}},"Worst":{"metrics":{"Time":{"current":[17.25]}}},"Average":{"metrics":{"Time":{"current":[12.478991596638656]}}}}},"splay":{"metrics":{"Score":{"current":[98.48678226590486]},"Time":["Geometric"]},"tests":{"First":{"metrics":{"Time":{"current":[91]}}},"Worst":{"metrics":{"Time":{"current":[58.50000000000001]}}},"Average":{"metrics":{"Time":{"current":[24.57983193277311]}}}}},"segmentation":{"metrics":{"Score":{"current":[30.287118623839532]},"Time":["Geometric"]},"tests":{"First":{"metrics":{"Time":{"current":[241.99999999999997]}}},"Worst":{"metrics":{"Time":{"current":[152]}}},"Average":{"metrics":{"Time":{"current":[122.31428571428572]}}}}},"richards-wasm":{"metrics":{"Score":{"current":[57.17366921829353]},"Time":["Geometric"]},"tests":{"Startup":{"metrics":{"Time":{"current":[8]}}},"Runtime":{"metrics":{"Time":{"current":[956]}}}}},"richards":{"metrics":{"Score":{"current":[271.4825281827819]},"Time":["Geometric"]},"tests":{"First":{"metrics":{"Time":{"current":[20]}}},"Worst":{"metrics":{"Time":{"current":[21.75]}}},"Average":{"metrics":{"Time":{"current":[14.361344537815128]}}}}},"regexp":{"metrics":{"Score":{"current":[239.0985986325555]},"Time":["Geometric"]},"tests":{"First":{"metrics":{"Time":{"current":[26]}}},"Worst":{"metrics":{"Time":{"current":[24.25]}}},"Average":{"metrics":{"Time":{"current":[14.504201680672269]}}}}},"regex-dna-SP":{"metrics":{"Score":{"current":[444.5980422150063]},"Time":["Geometric"]},"tests":{"First":{"metrics":{"Time":{"current":[12]}}},"Worst":{"metrics":{"Time":{"current":[13]}}},"Average":{"metrics":{"Time":{"current":[9.117647058823529]}}}}},"raytrace":{"metrics":{"Score":{"current":[260.4963998084951]},"Time":["Geometric"]},"tests":{"First":{"metrics":{"Time":{"current":[27]}}},"Worst":{"metrics":{"Time":{"current":[20.75]}}},"Average":{"metrics":{"Time":{"current":[12.621848739495798]}}}}},"quicksort-wasm":{"metrics":{"Score":{"current":[303.1695312954162]},"Time":["Geometric"]},"tests":{"Startup":{"metrics":{"Time":{"current":[8]}}},"Runtime":{"metrics":{"Time":{"current":[34]}}}}},"prepack-wtb":{"metrics":{"Score":{"current":[38.46198196697559]},"Time":["Geometric"]},"tests":{"First":{"metrics":{"Time":{"current":[177]}}},"Worst":{"metrics":{"Time":{"current":[116]}}},"Average":{"metrics":{"Time":{"current":[107]}}}}},"pdfjs":{"metrics":{"Score":{"current":[137.96122929248253]},"Time":["Geometric"]},"tests":{"First":{"metrics":{"Time":{"current":[62]}}},"Worst":{"metrics":{"Time":{"current":[36]}}},"Average":{"metrics":{"Time":{"current":[21.327731092436974]}}}}},"OfflineAssembler":{"metrics":{"Score":{"current":[45.26848267253425]},"Time":["Geometric"]},"tests":{"First":{"metrics":{"Time":{"current":[99]}}},"Worst":{"metrics":{"Time":{"current":[155.25]}}},"Average":{"metrics":{"Time":{"current":[87.67088607594937]}}}}},"octane-zlib":{"metrics":{"Score":{"current":[22.778156557636247]},"Time":["Geometric"]},"tests":{"First":{"metrics":{"Time":{"current":[252]}}},"Worst":{"metrics":{"Time":{"current":[208]}}},"Average":{"metrics":{"Time":{"current":[201.78571428571428]}}}}},"octane-code-load":{"metrics":{"Score":{"current":[639.1137726127176]},"Time":["Geometric"]},"tests":{"First":{"metrics":{"Time":{"current":[11]}}},"Worst":{"metrics":{"Time":{"current":[8.75]}}},"Average":{"metrics":{"Time":{"current":[4.974789915966387]}}}}},"navier-stokes":{"metrics":{"Score":{"current":[541.1751100773281]},"Time":["Geometric"]},"tests":{"First":{"metrics":{"Time":{"current":[22]}}},"Worst":{"metrics":{"Time":{"current":[6.75]}}},"Average":{"metrics":{"Time":{"current":[5.310924369747899]}}}}},"n-body-SP":{"metrics":{"Score":{"current":[706.9211838716564]},"Time":["Geometric"]},"tests":{"First":{"metrics":{"Time":{"current":[8]}}},"Worst":{"metrics":{"Time":{"current":[9.25]}}},"Average":{"metrics":{"Time":{"current":[4.781512605042017]}}}}},"multi-inspector-code-load":{"metrics":{"Score":{"current":[135.24754390267933]},"Time":["Geometric"]},"tests":{"First":{"metrics":{"Time":{"current":[43]}}},"Worst":{"metrics":{"Time":{"current":[39.5]}}},"Average":{"metrics":{"Time":{"current":[29.747899159663866]}}}}},"ML":{"metrics":{"Score":{"current":[35.35188919314548]},"Time":["Geometric"]},"tests":{"First":{"metrics":{"Time":{"current":[144]}}},"Worst":{"metrics":{"Time":{"current":[148.75]}}},"Average":{"metrics":{"Time":{"current":[132.08474576271186]}}}}},"mandreel":{"metrics":{"Score":{"current":[55.0755356502253]},"Time":["Geometric"]},"tests":{"First":{"metrics":{"Time":{"current":[124]}}},"Worst":{"metrics":{"Time":{"current":[81.5]}}},"Average":{"metrics":{"Time":{"current":[74.0379746835443]}}}}},"lebab-wtb":{"metrics":{"Score":{"current":[54.218170683876174]},"Time":["Geometric"]},"tests":{"First":{"metrics":{"Time":{"current":[129]}}},"Worst":{"metrics":{"Time":{"current":[83]}}},"Average":{"metrics":{"Time":{"current":[73.25]}}}}},"json-stringify-inspector":{"metrics":{"Score":{"current":[295.3055777480435]},"Time":["Geometric"]},"tests":{"First":{"metrics":{"Time":{"current":[17]}}},"Worst":{"metrics":{"Time":{"current":[17.5]}}},"Average":{"metrics":{"Time":{"current":[16.31578947368421]}}}}},"json-parse-inspector":{"metrics":{"Score":{"current":[180.09379366241123]},"Time":["Geometric"]},"tests":{"First":{"metrics":{"Time":{"current":[19]}}},"Worst":{"metrics":{"Time":{"current":[40]}}},"Average":{"metrics":{"Time":{"current":[28.157894736842106]}}}}},"jshint-wtb":{"metrics":{"Score":{"current":[64.52705325480771]},"Time":["Geometric"]},"tests":{"First":{"metrics":{"Time":{"current":[111.99999999999999]}}},"Worst":{"metrics":{"Time":{"current":[67]}}},"Average":{"metrics":{"Time":{"current":[62]}}}}},"HashSet-wasm":{"metrics":{"Score":{"current":[33.104598336201384]},"Time":["Geometric"]},"tests":{"Startup":{"metrics":{"Time":{"current":[12]}}},"Runtime":{"metrics":{"Time":{"current":[1901.0000000000002]}}}}},"hash-map":{"metrics":{"Score":{"current":[190.0290074766803]},"Time":["Geometric"]},"tests":{"First":{"metrics":{"Time":{"current":[31]}}},"Worst":{"metrics":{"Time":{"current":[30.75]}}},"Average":{"metrics":{"Time":{"current":[19.10924369747899]}}}}},"gcc-loops-wasm":{"metrics":{"Score":{"current":[33.15988181733069]},"Time":["Geometric"]},"tests":{"Startup":{"metrics":{"Time":{"current":[6.999999999999999]}}},"Runtime":{"metrics":{"Time":{"current":[3248]}}}}},"gbemu":{"metrics":{"Score":{"current":[116.53328831428978]},"Time":["Geometric"]},"tests":{"First":{"metrics":{"Time":{"current":[92]}}},"Worst":{"metrics":{"Time":{"current":[35.5]}}},"Average":{"metrics":{"Time":{"current":[24.18487394957983]}}}}},"gaussian-blur":{"metrics":{"Score":{"current":[397.30247257459985]},"Time":["Geometric"]},"tests":{"First":{"metrics":{"Time":{"current":[13]}}},"Worst":{"metrics":{"Time":{"current":[13.25]}}},"Average":{"metrics":{"Time":{"current":[11.571428571428571]}}}}},"float-mm.c":{"metrics":{"Score":{"current":[8.321089774642413]},"Time":["Geometric"]},"tests":{"First":{"metrics":{"Time":{"current":[499]}}},"Worst":{"metrics":{"Time":{"current":[740.5]}}},"Average":{"metrics":{"Time":{"current":[587.1428571428571]}}}}},"FlightPlanner":{"metrics":{"Score":{"current":[378.67454950198186]},"Time":["Geometric"]},"tests":{"First":{"metrics":{"Time":{"current":[18]}}},"Worst":{"metrics":{"Time":{"current":[19]}}},"Average":{"metrics":{"Time":{"current":[6.73109243697479]}}}}},"first-inspector-code-load":{"metrics":{"Score":{"current":[120.2276798255925]},"Time":["Geometric"]},"tests":{"First":{"metrics":{"Time":{"current":[38]}}},"Worst":{"metrics":{"Time":{"current":[53.25]}}},"Average":{"metrics":{"Time":{"current":[35.54621848739496]}}}}},"espree-wtb":{"metrics":{"Score":{"current":[29.411275823135774]},"Time":["Geometric"]},"tests":{"First":{"metrics":{"Time":{"current":[181]}}},"Worst":{"metrics":{"Time":{"current":[178]}}},"Average":{"metrics":{"Time":{"current":[152.5]}}}}},"earley-boyer":{"metrics":{"Score":{"current":[315.5053764300926]},"Time":["Geometric"]},"tests":{"First":{"metrics":{"Time":{"current":[19]}}},"Worst":{"metrics":{"Time":{"current":[20.25]}}},"Average":{"metrics":{"Time":{"current":[10.344537815126051]}}}}},"delta-blue":{"metrics":{"Score":{"current":[303.22761961951704]},"Time":["Geometric"]},"tests":{"First":{"metrics":{"Time":{"current":[27]}}},"Worst":{"metrics":{"Time":{"current":[16.25]}}},"Average":{"metrics":{"Time":{"current":[10.218487394957982]}}}}},"date-format-xparb-SP":{"metrics":{"Score":{"current":[176.22351029444758]},"Time":["Geometric"]},"tests":{"First":{"metrics":{"Time":{"current":[35]}}},"Worst":{"metrics":{"Time":{"current":[27.5]}}},"Average":{"metrics":{"Time":{"current":[23.73109243697479]}}}}},"date-format-tofte-SP":{"metrics":{"Score":{"current":[127.87583597391392]},"Time":["Geometric"]},"tests":{"First":{"metrics":{"Time":{"current":[44]}}},"Worst":{"metrics":{"Time":{"current":[39.5]}}},"Average":{"metrics":{"Time":{"current":[34.39495798319328]}}}}},"crypto-sha1-SP":{"metrics":{"Score":{"current":[294.9773624726326]},"Time":["Geometric"]},"tests":{"First":{"metrics":{"Time":{"current":[20]}}},"Worst":{"metrics":{"Time":{"current":[16.75]}}},"Average":{"metrics":{"Time":{"current":[14.53781512605042]}}}}},"crypto-md5-SP":{"metrics":{"Score":{"current":[245.3427521980804]},"Time":["Geometric"]},"tests":{"First":{"metrics":{"Time":{"current":[24]}}},"Worst":{"metrics":{"Time":{"current":[19.75]}}},"Average":{"metrics":{"Time":{"current":[17.857142857142858]}}}}},"crypto-aes-SP":{"metrics":{"Score":{"current":[391.53344661115136]},"Time":["Geometric"]},"tests":{"First":{"metrics":{"Time":{"current":[16]}}},"Worst":{"metrics":{"Time":{"current":[13.25]}}},"Average":{"metrics":{"Time":{"current":[9.823529411764707]}}}}},"crypto":{"metrics":{"Score":{"current":[685.205557421562]},"Time":["Geometric"]},"tests":{"First":{"metrics":{"Time":{"current":[9]}}},"Worst":{"metrics":{"Time":{"current":[7.5]}}},"Average":{"metrics":{"Time":{"current":[5.756302521008403]}}}}},"coffeescript-wtb":{"metrics":{"Score":{"current":[42.99574431968777]},"Time":["Geometric"]},"tests":{"First":{"metrics":{"Time":{"current":[162]}}},"Worst":{"metrics":{"Time":{"current":[103]}}},"Average":{"metrics":{"Time":{"current":[94.25]}}}}},"chai-wtb":{"metrics":{"Score":{"current":[86.70630198329543]},"Time":["Geometric"]},"tests":{"First":{"metrics":{"Time":{"current":[80]}}},"Worst":{"metrics":{"Time":{"current":[50.99999999999999]}}},"Average":{"metrics":{"Time":{"current":[47]}}}}},"cdjs":{"metrics":{"Score":{"current":[53.104103479615965]},"Time":["Geometric"]},"tests":{"First":{"metrics":{"Time":{"current":[104]}}},"Worst":{"metrics":{"Time":{"current":[97.33333333333333]}}},"Average":{"metrics":{"Time":{"current":[82.45762711864407]}}}}},"Box2D":{"metrics":{"Score":{"current":[270.3608887982111]},"Time":["Geometric"]},"tests":{"First":{"metrics":{"Time":{"current":[53]}}},"Worst":{"metrics":{"Time":{"current":[13.5]}}},"Average":{"metrics":{"Time":{"current":[8.840336134453782]}}}}},"bomb-workers":{"metrics":{"Score":{"current":[29.7558355823539]},"Time":["Geometric"]},"tests":{"First":{"metrics":{"Time":{"current":[145]}}},"Worst":{"metrics":{"Time":{"current":[211.5]}}},"Average":{"metrics":{"Time":{"current":[154.7088607594937]}}}}},"Basic":{"metrics":{"Score":{"current":[396.40660665461854]},"Time":["Geometric"]},"tests":{"First":{"metrics":{"Time":{"current":[20]}}},"Worst":{"metrics":{"Time":{"current":[12]}}},"Average":{"metrics":{"Time":{"current":[8.361344537815127]}}}}},"base64-SP":{"metrics":{"Score":{"current":[532.8753730466817]},"Time":["Geometric"]},"tests":{"First":{"metrics":{"Time":{"current":[13]}}},"Worst":{"metrics":{"Time":{"current":[9.5]}}},"Average":{"metrics":{"Time":{"current":[6.689075630252101]}}}}},"babylon-wtb":{"metrics":{"Score":{"current":[35.76670476214699]},"Time":["Geometric"]},"tests":{"First":{"metrics":{"Time":{"current":[167]}}},"Worst":{"metrics":{"Time":{"current":[133]}}},"Average":{"metrics":{"Time":{"current":[123]}}}}},"Babylon":{"metrics":{"Score":{"current":[321.09568272155786]},"Time":["Geometric"]},"tests":{"First":{"metrics":{"Time":{"current":[49]}}},"Worst":{"metrics":{"Time":{"current":[10.75]}}},"Average":{"metrics":{"Time":{"current":[7.168067226890756]}}}}},"async-fs":{"metrics":{"Score":{"current":[100.56890100084216]},"Time":["Geometric"]},"tests":{"First":{"metrics":{"Time":{"current":[52]}}},"Worst":{"metrics":{"Time":{"current":[54.666666666666664]}}},"Average":{"metrics":{"Time":{"current":[43.23076923076923]}}}}},"Air":{"metrics":{"Score":{"current":[291.2290237911513]},"Time":["Geometric"]},"tests":{"First":{"metrics":{"Time":{"current":[42]}}},"Worst":{"metrics":{"Time":{"current":[16.5]}}},"Average":{"metrics":{"Time":{"current":[7.302521008403361]}}}}},"ai-astar":{"metrics":{"Score":{"current":[587.3602168583692]},"Time":["Geometric"]},"tests":{"First":{"metrics":{"Time":{"current":[8]}}},"Worst":{"metrics":{"Time":{"current":[9.25]}}},"Average":{"metrics":{"Time":{"current":[8.336134453781513]}}}}},"acorn-wtb":{"metrics":{"Score":{"current":[32.10554234513838]},"Time":["Geometric"]},"tests":{"First":{"metrics":{"Time":{"current":[175]}}},"Worst":{"metrics":{"Time":{"current":[152]}}},"Average":{"metrics":{"Time":{"current":[142]}}}}},"3d-raytrace-SP":{"metrics":{"Score":{"current":[252.55142452082882]},"Time":["Geometric"]},"tests":{"First":{"metrics":{"Time":{"current":[25]}}},"Worst":{"metrics":{"Time":{"current":[18.75]}}},"Average":{"metrics":{"Time":{"current":[16.554621848739497]}}}}},"3d-cube-SP":{"metrics":{"Score":{"current":[238.005215106834]},"Time":["Geometric"]},"tests":{"First":{"metrics":{"Time":{"current":[23]}}},"Worst":{"metrics":{"Time":{"current":[22.5]}}},"Average":{"metrics":{"Time":{"current":[17.915966386554622]}}}}}}}}