{"JetStream2.0":{"metrics":{"Score":["Geometric"]},"tests":{"WSL":{"metrics":{"Score":{"current":[1.4371009767212575]},"Time":["Geometric"]},"tests":{"Stdlib":{"metrics":{"Time":{"current":[2311]}}},"MainRun":{"metrics":{"Time":{"current":[5238]}}}}},"UniPoker":{"metrics":{"Score":{"current":[463.6399797611499]},"Time":["Geometric"]},"tests":{"First":{"metrics":{"Time":{"current":[25]}}},"Worst":{"metrics":{"Time":{"current":[7.5]}}},"Average":{"metrics":{"Time":{"current":[6.689075630252101]}}}}},"uglify-js-wtb":{"metrics":{"Score":{"current":[47.75994237802912]},"Time":["Geometric"]},"tests":{"First":{"metrics":{"Time":{"current":[132]}}},"Worst":{"metrics":{"Time":{"current":[95]}}},"Average":{"metrics":{"Time":{"current":[91.5]}}}}},"typescript":{"metrics":{"Score":{"current":[22.693252616441132]},"Time":["Geometric"]},"tests":{"First":{"metrics":{"Time":{"current":[292]}}},"Worst":{"metrics":{"Time":{"current":[203.5]}}},"Average":{"metrics":{"Time":{"current":[180]}}}}},"tsf-wasm":{"metrics":{"Score":{"current":[98.55206599818044]},"Time":["Geometric"]},"tests":{"Startup":{"metrics":{"Time":{"current":[18]}}},"Runtime":{"metrics":{"Time":{"current":[143]}}}}},"tagcloud-SP":{"metrics":{"Score":{"current":[311.676611563463]},"Time":["Geometric"]},"tests":{"First":{"metrics":{"Time":{"current":[19]}}},"Worst":{"metrics":{"Time":{"current":[17.25]}}},"Average":{"metrics":{"Time":{"current":[12.596638655462185]}}}}},"string-unpack-code-SP":{"metrics":{"Score":{"current":[364.68493368237694]},"Time":["Geometric"]},"tests":{"First":{"metrics":{"Time":{"current":[17]}}},"Worst":{"metrics":{"Time":{"current":[15.25]}}},"Average":{"metrics":{"Time":{"current":[9.941176470588236]}}}}},"stanford-crypto-sha256":{"metrics":{"Score":{"current":[876.3846942701011]},"Time":["Geometric"]},"tests":{"First":{"metrics":{"Time":{"current":[6.999999999999999]}}},"Worst":{"metrics":{"Time":{"current":[5.5]}}},"Average":{"metrics":{"Time":{"current":[4.823529411764706]}}}}},"stanford-crypto-pbkdf2":{"metrics":{"Score":{"current":[745.7328442443697]},"Time":["Geometric"]},"tests":{"First":{"metrics":{"Time":{"current":[6.999999999999999]}}},"Worst":{"metrics":{"Time":{"current":[6.999999999999999]}}},"Average":{"metrics":{"Time":{"current":[6.151260504201681]}}}}},"stanford-crypto-aes":{"metrics":{"Score":{"current":[489.1188084598176]},"Time":["Geometric"]},"tests":{"First":{"metrics":{"Time":{"current":[16]}}},"Worst":{"metrics":{"Time":{"current":[8.75]}}},"Average":{"metrics":{"Time":{"current":[7.630252100840336]}}}}},"splay":{"metrics":{"Score":{"current":[209.27659839793154]},"Time":["Geometric"]},"tests":{"First":{"metrics":{"Time":{"current":[31]}}},"Worst":{"metrics":{"Time":{"current":[32]}}},"Average":{"metrics":{"Time":{"current":[13.747899159663866]}}}}},"segmentation":{"metrics":{"Score":{"current":[55.30615621895618]},"Time":["Geometric"]},"tests":{"First":{"metrics":{"Time":{"current":[140]}}},"Worst":{"metrics":{"Time":{"current":[73.33333333333333]}}},"Average":{"metrics":{"Time":{"current":[71.97142857142858]}}}}},"richards-wasm":{"metrics":{"Score":{"current":[109.76425998969034]},"Time":["Geometric"]},"tests":{"Startup":{"metrics":{"Time":{"current":[5]}}},"Runtime":{"metrics":{"Time":{"current":[415]}}}}},"richards":{"metrics":{"Score":{"current":[422.5748253062777]},"Time":["Geometric"]},"tests":{"First":{"metrics":{"Time":{"current":[18]}}},"Worst":{"metrics":{"Time":{"current":[10.5]}}},"Average":{"metrics":{"Time":{"current":[8.764705882352942]}}}}},"regexp":{"metrics":{"Score":{"current":[470.43018206691465]},"Time":["Geometric"]},"tests":{"First":{"metrics":{"Time":{"current":[8]}}},"Worst":{"metrics":{"Time":{"current":[19]}}},"Average":{"metrics":{"Time":{"current":[7.899159663865546]}}}}},"regex-dna-SP":{"metrics":{"Score":{"current":[593.1480328992293]},"Time":["Geometric"]},"tests":{"First":{"metrics":{"Time":{"current":[10]}}},"Worst":{"metrics":{"Time":{"current":[8]}}},"Average":{"metrics":{"Time":{"current":[7.487394957983194]}}}}},"raytrace":{"metrics":{"Score":{"current":[598.2775537316934]},"Time":["Geometric"]},"tests":{"First":{"metrics":{"Time":{"current":[13]}}},"Worst":{"metrics":{"Time":{"current":[7.25]}}},"Average":{"metrics":{"Time":{"current":[6.19327731092437]}}}}},"quicksort-wasm":{"metrics":{"Score":{"current":[472.45559126153404]},"Time":["Geometric"]},"tests":{"Startup":{"metrics":{"Time":{"current":[4]}}},"Runtime":{"metrics":{"Time":{"current":[27.999999999999996]}}}}},"prepack-wtb":{"metrics":{"Score":{"current":[78.8577632001763]},"Time":["Geometric"]},"tests":{"First":{"metrics":{"Time":{"current":[86]}}},"Worst":{"metrics":{"Time":{"current":[56.99999999999999]}}},"Average":{"metrics":{"Time":{"current":[52]}}}}},"pdfjs":{"metrics":{"Score":{"current":[247.4393924778068]},"Time":["Geometric"]},"tests":{"First":{"metrics":{"Time":{"current":[27.999999999999996]}}},"Worst":{"metrics":{"Time":{"current":[21.5]}}},"Average":{"metrics":{"Time":{"current":[13.705882352941176]}}}}},"OfflineAssembler":{"metrics":{"Score":{"current":[72.18173738733223]},"Time":["Geometric"]},"tests":{"First":{"metrics":{"Time":{"current":[74]}}},"Worst":{"metrics":{"Time":{"current":[93.5]}}},"Average":{"metrics":{"Time":{"current":[48.037974683544306]}}}}},"octane-zlib":{"metrics":{"Score":{"current":[34.047881271068725]},"Time":["Geometric"]},"tests":{"First":{"metrics":{"Time":{"current":[169]}}},"Worst":{"metrics":{"Time":{"current":[137.5]}}},"Average":{"metrics":{"Time":{"current":[136.28571428571428]}}}}},"octane-code-load":{"metrics":{"Score":{"current":[1024.725986345568]},"Time":["Geometric"]},"tests":{"First":{"metrics":{"Time":{"current":[6]}}},"Worst":{"metrics":{"Time":{"current":[6]}}},"Average":{"metrics":{"Time":{"current":[3.2268907563025215]}}}}},"navier-stokes":{"metrics":{"Score":{"current":[636.827120603497]},"Time":["Geometric"]},"tests":{"First":{"metrics":{"Time":{"current":[11]}}},"Worst":{"metrics":{"Time":{"current":[6.999999999999999]}}},"Average":{"metrics":{"Time":{"current":[6.285714285714286]}}}}},"n-body-SP":{"metrics":{"Score":{"current":[1345.6241372122386]},"Time":["Geometric"]},"tests":{"First":{"metrics":{"Time":{"current":[3]}}},"Worst":{"metrics":{"Time":{"current":[5]}}},"Average":{"metrics":{"Time":{"current":[3.4201680672268906]}}}}},"multi-inspector-code-load":{"metrics":{"Score":{"current":[220.57921223627744]},"Time":["Geometric"]},"tests":{"First":{"metrics":{"Time":{"current":[22]}}},"Worst":{"metrics":{"Time":{"current":[26.25]}}},"Average":{"metrics":{"Time":{"current":[20.168067226890756]}}}}},"ML":{"metrics":{"Score":{"current":[64.95127900280967]},"Time":["Geometric"]},"tests":{"First":{"metrics":{"Time":{"current":[84]}}},"Worst":{"metrics":{"Time":{"current":[74]}}},"Average":{"metrics":{"Time":{"current":[73.38983050847457]}}}}},"mandreel":{"metrics":{"Score":{"current":[107.45918087229752]},"Time":["Geometric"]},"tests":{"First":{"metrics":{"Time":{"current":[65]}}},"Worst":{"metrics":{"Time":{"current":[40.5]}}},"Average":{"metrics":{"Time":{"current":[38.265822784810126]}}}}},"lebab-wtb":{"metrics":{"Score":{"current":[85.9038800566733]},"Time":["Geometric"]},"tests":{"First":{"metrics":{"Time":{"current":[79]}}},"Worst":{"metrics":{"Time":{"current":[52]}}},"Average":{"metrics":{"Time":{"current":[48]}}}}},"json-stringify-inspector":{"metrics":{"Score":{"current":[415.9583926768784]},"Time":["Geometric"]},"tests":{"First":{"metrics":{"Time":{"current":[12]}}},"Worst":{"metrics":{"Time":{"current":[12.5]}}},"Average":{"metrics":{"Time":{"current":[11.578947368421053]}}}}},"json-parse-inspector":{"metrics":{"Score":{"current":[222.18180663361605]},"Time":["Geometric"]},"tests":{"First":{"metrics":{"Time":{"current":[15]}}},"Worst":{"metrics":{"Time":{"current":[36]}}},"Average":{"metrics":{"Time":{"current":[21.105263157894736]}}}}},"jshint-wtb":{"metrics":{"Score":{"current":[95.69065297366068]},"Time":["Geometric"]},"tests":{"First":{"metrics":{"Time":{"current":[67]}}},"Worst":{"metrics":{"Time":{"current":[50.99999999999999]}}},"Average":{"metrics":{"Time":{"current":[41.75]}}}}},"HashSet-wasm":{"metrics":{"Score":{"current":[48.7671446650544]},"Time":["Geometric"]},"tests":{"Startup":{"metrics":{"Time":{"current":[9]}}},"Runtime":{"metrics":{"Time":{"current":[1168]}}}}},"hash-map":{"metrics":{"Score":{"current":[303.360730970951]},"Time":["Geometric"]},"tests":{"First":{"metrics":{"Time":{"current":[22]}}},"Worst":{"metrics":{"Time":{"current":[17.25]}}},"Average":{"metrics":{"Time":{"current":[11.798319327731093]}}}}},"gcc-loops-wasm":{"metrics":{"Score":{"current":[33.98609301719274]},"Time":["Geometric"]},"tests":{"Startup":{"metrics":{"Time":{"current":[6.999999999999999]}}},"Runtime":{"metrics":{"Time":{"current":[3092]}}}}},"gbemu":{"metrics":{"Score":{"current":[156.94932369350562]},"Time":["Geometric"]},"tests":{"First":{"metrics":{"Time":{"current":[56.99999999999999]}}},"Worst":{"metrics":{"Time":{"current":[27]}}},"Average":{"metrics":{"Time":{"current":[21.008403361344538]}}}}},"gaussian-blur":{"metrics":{"Score":{"current":[566.3352578610824]},"Time":["Geometric"]},"tests":{"First":{"metrics":{"Time":{"current":[9]}}},"Worst":{"metrics":{"Time":{"current":[9]}}},"Average":{"metrics":{"Time":{"current":[8.495798319327731]}}}}},"float-mm.c":{"metrics":{"Score":{"current":[13.462163442857227]},"Time":["Geometric"]},"tests":{"First":{"metrics":{"Time":{"current":[369]}}},"Worst":{"metrics":{"Time":{"current":[376.5]}}},"Average":{"metrics":{"Time":{"current":[368.7857142857143]}}}}},"FlightPlanner":{"metrics":{"Score":{"current":[962.1109659047793]},"Time":["Geometric"]},"tests":{"First":{"metrics":{"Time":{"current":[10]}}},"Worst":{"metrics":{"Time":{"current":[4.25]}}},"Average":{"metrics":{"Time":{"current":[3.302521008403361]}}}}},"first-inspector-code-load":{"metrics":{"Score":{"current":[229.55792529146993]},"Time":["Geometric"]},"tests":{"First":{"metrics":{"Time":{"current":[22]}}},"Worst":{"metrics":{"Time":{"current":[23.25]}}},"Average":{"metrics":{"Time":{"current":[20.201680672268907]}}}}},"espree-wtb":{"metrics":{"Score":{"current":[47.47394784194893]},"Time":["Geometric"]},"tests":{"First":{"metrics":{"Time":{"current":[113.99999999999999]}}},"Worst":{"metrics":{"Time":{"current":[111.99999999999999]}}},"Average":{"metrics":{"Time":{"current":[91.5]}}}}},"earley-boyer":{"metrics":{"Score":{"current":[523.9769049191345]},"Time":["Geometric"]},"tests":{"First":{"metrics":{"Time":{"current":[11]}}},"Worst":{"metrics":{"Time":{"current":[12.5]}}},"Average":{"metrics":{"Time":{"current":[6.319327731092437]}}}}},"delta-blue":{"metrics":{"Score":{"current":[578.502107370979]},"Time":["Geometric"]},"tests":{"First":{"metrics":{"Time":{"current":[16]}}},"Worst":{"metrics":{"Time":{"current":[6.999999999999999]}}},"Average":{"metrics":{"Time":{"current":[5.764705882352941]}}}}},"date-format-xparb-SP":{"metrics":{"Score":{"current":[241.84887400756548]},"Time":["Geometric"]},"tests":{"First":{"metrics":{"Time":{"current":[25]}}},"Worst":{"metrics":{"Time":{"current":[19.5]}}},"Average":{"metrics":{"Time":{"current":[18.126050420168067]}}}}},"date-format-tofte-SP":{"metrics":{"Score":{"current":[188.73704271838338]},"Time":["Geometric"]},"tests":{"First":{"metrics":{"Time":{"current":[29]}}},"Worst":{"metrics":{"Time":{"current":[26.5]}}},"Average":{"metrics":{"Time":{"current":[24.19327731092437]}}}}},"crypto-sha1-SP":{"metrics":{"Score":{"current":[489.01624632461136]},"Time":["Geometric"]},"tests":{"First":{"metrics":{"Time":{"current":[12]}}},"Worst":{"metrics":{"Time":{"current":[10]}}},"Average":{"metrics":{"Time":{"current":[8.907563025210084]}}}}},"crypto-md5-SP":{"metrics":{"Score":{"current":[436.00998690672196]},"Time":["Geometric"]},"tests":{"First":{"metrics":{"Time":{"current":[15]}}},"Worst":{"metrics":{"Time":{"current":[12]}}},"Average":{"metrics":{"Time":{"current":[8.378151260504202]}}}}},"crypto-aes-SP":{"metrics":{"Score":{"current":[581.8740708045694]},"Time":["Geometric"]},"tests":{"First":{"metrics":{"Time":{"current":[11]}}},"Worst":{"metrics":{"Time":{"current":[8]}}},"Average":{"metrics":{"Time":{"current":[7.2100840336134455]}}}}},"crypto":{"metrics":{"Score":{"current":[839.3855399018589]},"Time":["Geometric"]},"tests":{"First":{"metrics":{"Time":{"current":[8]}}},"Worst":{"metrics":{"Time":{"current":[6]}}},"Average":{"metrics":{"Time":{"current":[4.4033613445378155]}}}}},"coffeescript-wtb":{"metrics":{"Score":{"current":[76.07142754343624]},"Time":["Geometric"]},"tests":{"First":{"metrics":{"Time":{"current":[93]}}},"Worst":{"metrics":{"Time":{"current":[59.00000000000001]}}},"Average":{"metrics":{"Time":{"current":[51.75]}}}}},"chai-wtb":{"metrics":{"Score":{"current":[119.09479040119291]},"Time":["Geometric"]},"tests":{"First":{"metrics":{"Time":{"current":[50]}}},"Worst":{"metrics":{"Time":{"current":[40]}}},"Average":{"metrics":{"Time":{"current":[37]}}}}},"cdjs":{"metrics":{"Score":{"current":[81.76572189722287]},"Time":["Geometric"]},"tests":{"First":{"metrics":{"Time":{"current":[66]}}},"Worst":{"metrics":{"Time":{"current":[61]}}},"Average":{"metrics":{"Time":{"current":[56.79661016949152]}}}}},"Box2D":{"metrics":{"Score":{"current":[439.3434706739564]},"Time":["Geometric"]},"tests":{"First":{"metrics":{"Time":{"current":[27.999999999999996]}}},"Worst":{"metrics":{"Time":{"current":[8.5]}}},"Average":{"metrics":{"Time":{"current":[6.19327731092437]}}}}},"bomb-workers":{"metrics":{"Score":{"current":[57.46964553290159]},"Time":["Geometric"]},"tests":{"First":{"metrics":{"Time":{"current":[91]}}},"Worst":{"metrics":{"Time":{"current":[93.25]}}},"Average":{"metrics":{"Time":{"current":[77.60759493670885]}}}}},"Basic":{"metrics":{"Score":{"current":[730.5698301496126]},"Time":["Geometric"]},"tests":{"First":{"metrics":{"Time":{"current":[11]}}},"Worst":{"metrics":{"Time":{"current":[6]}}},"Average":{"metrics":{"Time":{"current":[4.857142857142857]}}}}},"base64-SP":{"metrics":{"Score":{"current":[693.9059417186468]},"Time":["Geometric"]},"tests":{"First":{"metrics":{"Time":{"current":[8]}}},"Worst":{"metrics":{"Time":{"current":[8.75]}}},"Average":{"metrics":{"Time":{"current":[5.34453781512605]}}}}},"babylon-wtb":{"metrics":{"Score":{"current":[56.750295921464854]},"Time":["Geometric"]},"tests":{"First":{"metrics":{"Time":{"current":[94]}}},"Worst":{"metrics":{"Time":{"current":[89]}}},"Average":{"metrics":{"Time":{"current":[81.75]}}}}},"Babylon":{"metrics":{"Score":{"current":[634.7309906903904]},"Time":["Geometric"]},"tests":{"First":{"metrics":{"Time":{"current":[19]}}},"Worst":{"metrics":{"Time":{"current":[6.5]}}},"Average":{"metrics":{"Time":{"current":[3.9579831932773115]}}}}},"async-fs":{"metrics":{"Score":{"current":[123.86224300831654]},"Time":["Geometric"]},"tests":{"First":{"metrics":{"Time":{"current":[42]}}},"Worst":{"metrics":{"Time":{"current":[40.666666666666664]}}},"Average":{"metrics":{"Time":{"current":[38.512820512820504]}}}}},"Air":{"metrics":{"Score":{"current":[473.28336011825087]},"Time":["Geometric"]},"tests":{"First":{"metrics":{"Time":{"current":[21]}}},"Worst":{"metrics":{"Time":{"current":[11.5]}}},"Average":{"metrics":{"Time":{"current":[4.882352941176472]}}}}},"ai-astar":{"metrics":{"Score":{"current":[697.4328431780566]},"Time":["Geometric"]},"tests":{"First":{"metrics":{"Time":{"current":[6.999999999999999]}}},"Worst":{"metrics":{"Time":{"current":[8]}}},"Average":{"metrics":{"Time":{"current":[6.579831932773109]}}}}},"acorn-wtb":{"metrics":{"Score":{"current":[50.71930174551025]},"Time":["Geometric"]},"tests":{"First":{"metrics":{"Time":{"current":[103]}}},"Worst":{"metrics":{"Time":{"current":[106]}}},"Average":{"metrics":{"Time":{"current":[87.75]}}}}},"3d-raytrace-SP":{"metrics":{"Score":{"current":[301.34165938166274]},"Time":["Geometric"]},"tests":{"First":{"metrics":{"Time":{"current":[24]}}},"Worst":{"metrics":{"Time":{"current":[15]}}},"Average":{"metrics":{"Time":{"current":[12.6890756302521]}}}}},"3d-cube-SP":{"metrics":{"Score":{"current":[262.30858974506464]},"Time":["Geometric"]},"tests":{"First":{"metrics":{"Time":{"current":[22]}}},"Worst":{"metrics":{"Time":{"current":[18.5]}}},"Average":{"metrics":{"Time":{"current":[17.016806722689076]}}}}}}}}