{"Multiply": {"Score": 840.37, "80 percent CI": {"min": 803.99, "max": 879.51, "percentMin": 4.33, "percentMax": 4.66}, "Time Complexity": {"average": 842.38, "percent": 9.83}, "Raw Complexity": {"average": 830.5, "stdev": 3.63}}, "Canvas Arcs": {"Score": 1173.53, "80 percent CI": {"min": 1120.09, "max": 1237.72, "percentMin": 4.55, "percentMax": 5.47}, "Time Complexity": {"average": 1179.77, "percent": 7.51}, "Raw Complexity": {"average": 1164.58, "stdev": 4.09}}, "Leaves": {"Score": 738.1, "80 percent CI": {"min": 709.14, "max": 768.99, "percentMin": 3.92, "percentMax": 4.18}, "Time Complexity": {"average": 715.8, "percent": 11.07}, "Raw Complexity": {"average": 725.72, "stdev": 3.1}}, "Paths": {"Score": 4271.64, "80 percent CI": {"min": 4076.24, "max": 4460.67, "percentMin": 4.57, "percentMax": 4.43}, "Time Complexity": {"average": 4243.56, "percent": 4.4}, "Raw Complexity": {"average": 4319.04, "stdev": 3.74}}, "Canvas Lines": {"Score": 12715.37, "80 percent CI": {"min": 12019.79, "max": 13296.96, "percentMin": 5.47, "percentMax": 4.57}, "Time Complexity": {"average": 12671.75, "percent": 10.84}, "Raw Complexity": {"average": 12592.05, "stdev": 4.22}}, "Images": {"Score": 26.09, "80 percent CI": {"min": 25.34, "max": 26.71, "percentMin": 2.88, "percentMax": 2.36}, "Time Complexity": {"average": 24.87, "percent": 22.01}, "Raw Complexity": {"average": 26.07, "stdev": 2.01}}, "Design": {"Score": 160.45, "80 percent CI": {"min": 155.4, "max": 165.35, "percentMin": 3.15, "percentMax": 3.06}, "Time Complexity": {"average": 160.58, "percent": 10.19}, "Raw Complexity": {"average": 159.98, "stdev": 1.85}}, "Suits": {"Score": 1058.31, "80 percent CI": {"min": 1023.49, "max": 1090.17, "percentMin": 3.29, "percentMax": 3.01}, "Time Complexity": {"average": 1063.27, "percent": 12.8}, "Raw Complexity": {"average": 1046.67, "stdev": 2.43}}, "Global Score": {"Geomean": 1058.31, "fps": 60.0, "80 CI lower percentage": 4.02, "80 CI upper percentage": 3.96}}