{"Multiply": {"Score": 2067.72, "80 percent CI": {"min": 2003.95, "max": 2121.28, "percentMin": 3.08, "percentMax": 2.59}, "Time Complexity": {"average": 2070.64, "percent": 3.5}, "Raw Complexity": {"average": 2077.5, "stdev": 3.33}}, "Canvas Arcs": {"Score": 1374.53, "80 percent CI": {"min": 1355.88, "max": 1383.62, "percentMin": 1.36, "percentMax": 0.66}, "Time Complexity": {"average": 1425.45, "percent": 7.11}, "Raw Complexity": {"average": 1351.72, "stdev": 0.94}}, "Leaves": {"Score": 2008.49, "80 percent CI": {"min": 1960.72, "max": 2040.77, "percentMin": 2.38, "percentMax": 1.61}, "Time Complexity": {"average": 1915.42, "percent": 12.11}, "Raw Complexity": {"average": 2003.34, "stdev": 2.05}}, "Paths": {"Score": 4381.9, "80 percent CI": {"min": 4361.43, "max": 4400.09, "percentMin": 0.47, "percentMax": 0.42}, "Time Complexity": {"average": 4377.11, "percent": 1.12}, "Raw Complexity": {"average": 4372.2, "stdev": 0.73}}, "Canvas Lines": {"Score": 16657.7, "80 percent CI": {"min": 15782.88, "max": 17557.44, "percentMin": 5.25, "percentMax": 5.4}, "Time Complexity": {"average": 16899.39, "percent": 4.9}, "Raw Complexity": {"average": 16763.91, "stdev": 4.46}}, "Images": {"Score": 289.74, "80 percent CI": {"min": 282.54, "max": 295.96, "percentMin": 2.48, "percentMax": 2.15}, "Time Complexity": {"average": 285.52, "percent": 9.19}, "Raw Complexity": {"average": 286.39, "stdev": 2.09}}, "Design": {"Score": 346.39, "80 percent CI": {"min": 336.39, "max": 353.21, "percentMin": 2.89, "percentMax": 1.97}, "Time Complexity": {"average": 354.6, "percent": 6.06}, "Raw Complexity": {"average": 349.25, "stdev": 1.2}}, "Suits": {"Score": 2861.32, "80 percent CI": {"min": 2761.62, "max": 2909.51, "percentMin": 3.48, "percentMax": 1.68}, "Time Complexity": {"average": 3129.01, "percent": 25.92}, "Raw Complexity": {"average": 2848.83, "stdev": 1.99}}, "Global Score": {"Geomean": 2861.32, "fps": 60.0, "80 CI lower percentage": 2.68, "80 CI upper percentage": 2.05}}