{"Multiply": {"Score": 860.86, "80 percent CI": {"min": 812.9, "max": 894.55, "percentMin": 5.57, "percentMax": 3.91}, "Time Complexity": {"average": 867.75, "percent": 8.46}, "Raw Complexity": {"average": 853.06, "stdev": 3.76}}, "Canvas Arcs": {"Score": 1094.16, "80 percent CI": {"min": 1022.5, "max": 1155.91, "percentMin": 6.55, "percentMax": 5.64}, "Time Complexity": {"average": 1137.09, "percent": 14.11}, "Raw Complexity": {"average": 1087.64, "stdev": 4.31}}, "Leaves": {"Score": 782.71, "80 percent CI": {"min": 747.09, "max": 807.77, "percentMin": 4.55, "percentMax": 3.2}, "Time Complexity": {"average": 731.1, "percent": 18.32}, "Raw Complexity": {"average": 770.29, "stdev": 2.88}}, "Paths": {"Score": 4070.42, "80 percent CI": {"min": 3864.29, "max": 4282.75, "percentMin": 5.06, "percentMax": 5.22}, "Time Complexity": {"average": 4102.67, "percent": 12.58}, "Raw Complexity": {"average": 4039.25, "stdev": 4.09}}, "Canvas Lines": {"Score": 13141.18, "80 percent CI": {"min": 12509.63, "max": 13872.41, "percentMin": 4.81, "percentMax": 5.56}, "Time Complexity": {"average": 13114.29, "percent": 7.47}, "Raw Complexity": {"average": 12936.04, "stdev": 4.15}}, "Images": {"Score": 26.54, "80 percent CI": {"min": 25.63, "max": 27.1, "percentMin": 3.44, "percentMax": 2.1}, "Time Complexity": {"average": 26.2, "percent": 18.3}, "Raw Complexity": {"average": 26.48, "stdev": 2.09}}, "Design": {"Score": 158.31, "80 percent CI": {"min": 153.3, "max": 162.27, "percentMin": 3.17, "percentMax": 2.5}, "Time Complexity": {"average": 159.18, "percent": 10.12}, "Raw Complexity": {"average": 156.19, "stdev": 1.82}}, "Suits": {"Score": 1026.86, "80 percent CI": {"min": 983.25, "max": 1059.17, "percentMin": 4.25, "percentMax": 3.15}, "Time Complexity": {"average": 1015.91, "percent": 10.71}, "Raw Complexity": {"average": 511.13, "stdev": 2.83}}, "Global Score": {"Geomean": 1026.86, "fps": 60.0, "80 CI lower percentage": 4.68, "80 CI upper percentage": 3.9}}